{
  "shortDescription": "IEEE YTU CASMarine İnsansız Su Altı Sistemleri Takımı",
  "profilePhoto": "/images/uploads/screenshot-2026-03-11-160722.png",
  "name": "CASMarine",
  "socialLinks": {
    "instagram": "https://www.instagram.com/ieeeytucas/",
    "linkedin": "https://www.linkedin.com/company/casmarine/",
    "twitter": "https://x.com/ieeeytucas",
    "website": "https://casmarine.net/"
  },
  "fullDescription": "CASMarine, 2016’dan bu yana insansız su altı sistemleri geliştiren ve üreten, bu dalda ulusal ve uluslararası yarışmalara katılarak kendisine, üniversitesine ve ülkesine değer katan, geleceği şekillendirecek, fikri hür mühendis adaylarından oluşan öğrenci takımıdır. Amacı ülkemiz ve dünyadaki su altı problemlerine karşı çözümler üretmek ve bu alandaki AR&GE çalışmalarında yer almaktır.",
  "bannerImage": "/images/uploads/screenshot-2026-03-11-161349.png",
  "galleryPhotos": [
    "/images/uploads/header-bg.png",
    "/images/uploads/screenshot-2026-03-11-161727.png",
    "/images/uploads/screenshot-2026-03-11-161759.png",
    "/images/uploads/screenshot-2026-03-11-161833.png"
  ],
  "location": "Yıldız Teknik Üniversitesi Davutpaşa Kampüsü, Kulüpler Vadisi",
  "contactEmail": "ieeeytucas@gmail.com",
  "category": "Otonom Araç"
}